llmshield_spanish_corpus/__init__.py
llmshield_spanish_corpus/loader.py
llmshield_spanish_corpus/data/spanish.txt
llmshield_spanish_corpus-1.0.2.dist-info/METADATA
llmshield_spanish_corpus-1.0.2.dist-info/WHEEL
llmshield_spanish_corpus-1.0.2.dist-info/top_level.txt
llmshield_spanish_corpus-1.0.2.dist-info/RECORD
