Metadata-Version: 2.4
Name: llmshield_spanish_corpus
Version: 1.0.2
Summary: Spanish language corpus for LLMShield entity detection.
Author-email: Aditya Dedhia <aditya@brainpolo.com>, Sebastian Andres El Khoury Seoane <sebasandres0694@gmail.com>
Project-URL: Homepage, https://github.com/brainpolo/llmshield_spanish_corpus
Project-URL: Issues, https://github.com/brainpolo/llmshield_spanish_corpus/issues
Keywords: llm,ai,security,privacy,nlp,corpus,spanish,llmshield
Classifier: Development Status :: 3 - Alpha
Classifier: Intended Audience :: Developers
Classifier: Operating System :: OS Independent
Classifier: Programming Language :: Python :: 3
Classifier: Topic :: Text Processing :: Linguistic
Classifier: Topic :: Software Development :: Libraries :: Python Modules
Requires-Python: >=3.12
Provides-Extra: dev
Requires-Dist: build>=1.2.2; extra == "dev"
Requires-Dist: twine>=6.1.0; extra == "dev"
Requires-Dist: ruff>=0.11.13; extra == "dev"
